nanoutils/__init__.py
nanoutils/_catch_err.py
nanoutils/_dtype_mapping.py
nanoutils/_lazy_import.py
nanoutils/_partial.py
nanoutils/_partial.pyi
nanoutils/_seq_view.py
nanoutils/_set_attr.py
nanoutils/_user_dict.py
nanoutils/_version.py
nanoutils/empty.py
nanoutils/file_container.py
nanoutils/hdf5_utils.py
nanoutils/numpy_utils.py
nanoutils/py.typed
nanoutils/schema.py
nanoutils/testing_utils.py
nanoutils/typing_utils.py
nanoutils/utils.py
nanoutils/yaml_utils.py
Nano_Utils-2.3.5.dist-info/LICENSE.md
Nano_Utils-2.3.5.dist-info/METADATA
Nano_Utils-2.3.5.dist-info/WHEEL
Nano_Utils-2.3.5.dist-info/top_level.txt
Nano_Utils-2.3.5.dist-info/RECORD
